pynautobot/__init__.py
pynautobot/core/__init__.py
pynautobot/core/api.py
pynautobot/core/app.py
pynautobot/core/endpoint.py
pynautobot/core/graphql.py
pynautobot/core/query.py
pynautobot/core/response.py
pynautobot/core/util.py
pynautobot/models/__init__.py
pynautobot/models/circuits.py
pynautobot/models/cloud.py
pynautobot/models/dcim.py
pynautobot/models/extras.py
pynautobot/models/ipam.py
pynautobot/models/users.py
pynautobot/models/virtualization.py
pynautobot-3.0.0.dist-info/LICENSE
pynautobot-3.0.0.dist-info/METADATA
pynautobot-3.0.0.dist-info/NOTICE
pynautobot-3.0.0.dist-info/WHEEL
pynautobot-3.0.0.dist-info/RECORD
