Metadata-Version: 2.1
Name: pynautobot
Version: 3.0.0
Summary: Nautobot API client library
Home-page: https://nautobot.com
License: Apache-2.0
Keywords: Nautobot
Author: Network to Code, LLC
Author-email: opensource@networktocode.com
Requires-Python: >=3.10,<4.0
Classifier: Development Status :: 5 - Production/Stable
Classifier: Intended Audience :: Developers
Classifier: License :: OSI Approved :: Apache Software License
Classifier: Programming Language :: Python :: 3
Classifier: Programming Language :: Python :: 3.10
Classifier: Programming Language :: Python :: 3.11
Classifier: Programming Language :: Python :: 3.12
Classifier: Programming Language :: Python :: 3.13
Requires-Dist: packaging (>=23.2)
Requires-Dist: requests (>=2.30.0,<3.0.0)
Requires-Dist: urllib3 (>=1.21.1,<3)
Project-URL: Documentation, https://pynautobot.readthedocs.io
Project-URL: Repository, https://github.com/nautobot/pynautobot
